lilbulb/__init__.py
lilbulb-1.0.3.dist-info/LICENSE
lilbulb-1.0.3.dist-info/METADATA
lilbulb-1.0.3.dist-info/WHEEL
lilbulb-1.0.3.dist-info/top_level.txt
lilbulb-1.0.3.dist-info/RECORD
